saten/__init__.py
saten-1.0.0.dist-info/LICENSE
saten-1.0.0.dist-info/METADATA
saten-1.0.0.dist-info/WHEEL
saten-1.0.0.dist-info/top_level.txt
saten-1.0.0.dist-info/RECORD
